Metadata-Version: 1.0
Name: pyppackageexample
Version: 0.0.1
Summary: Paquete de prueba para una clase de Udemy
Home-page: https://github.com/brjmrtn/pyppackageexample
Author: Borja Martín Medina
Author-email: UNKNOWN
License: MIT
Platform: UNKNOWN
